converter/__init__.py
converter/converts.py
converter/mainss.py
converter/test.py
TempConverter-1.1.dist-info/METADATA
TempConverter-1.1.dist-info/WHEEL
TempConverter-1.1.dist-info/top_level.txt
TempConverter-1.1.dist-info/RECORD
