Metadata-Version: 2.1
Name: TempConverter
Version: 1.1
Summary: A small package to convert temperature
Home-page: 
Author: Akash
Author-email: akash9129@gmail.com
Classifier: Programming Language :: Python :: 3
Classifier: License :: OSI Approved :: MIT License
Classifier: Operating System :: OS Independent
Requires-Python: >=3.6
